Workbook

Sheet A. Start
A1: Kalkulationstool Light | B1: Vesion 1.0
A3: Projektname | B3: Testkalkulation Kombinationen | D3: Start Leistung | E3: 46492
A4: Kundenname | B4: Testkunde | D4: Ende Leistung | E4: 48318
A5: Projektstandort | B5: UT | D5: Laufzeit [Monate] | E5: =DATEDIF(E3,E4+1,"m") -> 60
A6: Kundenkontakt | B6: Mustermann | D6: Laufzeit [Jahre] | E6: =E5/12 -> 5
A8: Geschäftsbereich | B8: VIAS | D8: Datum Kalkulation | E8: 46111
A9: Service-Line | B9: LOG | D9: Bearbeiter | E9: Kästner
A11: Farblogik
A13: Eingabefeld | B13: Eingabe
A14: Ausgabefeld | B14: nicht befüllen!
A15: Highlights | B15: nicht befüllen!
A17: Kurzanleitung
A19: Step 1 | B19: Reiter "Start" mit allgemeinen Projektdaten befüllen
A20: Step 2 | B20: Reiter "Basisdaten" mit Kalkulationsgrunddaten befüllen. Felder für die Berechnung des Bruttofaktors können optional befüllt werden, um Personalmehrbedarfe zu kalkulieren, ist jedoch nicht erfoderlich für die Berechnung des Gesamtumsatzes. Eingabefelder für die Personalnebenkosten beruhen auf dem deutschen Sozialversicherungssystem. Bei Abweichungen in anderen Ländern oder zur Vereinfachung können die Detailfelder auf 0,00% gesetzt werden und dafür die "sonstigen Anteile/Zulagen/Nebenkosten-Felder" genutzt werden, um einen Gesamtwert an Zuschlägen zu definieren. Das Eingabefeld "Zuschlag SVS für zusätzliche Tätigkeiten" definiert die Zuschläge für z.B. Sonderleistungen oder andere spezielle Bereiche und wird separat auf den Stundenlohn aufgeschlagen, sodass Löhne mit und ohne Zuschläge ersichtlich sind. Analoge Berechnung für Gehälter.
A21: Step 3 | B21: Reiter "Personalkosten" mit Funktionen in Tabelle Gehälter (Eingabe Jahresgehalt) oder Tabelle Löhne (Eingabe Stundenlohn) befüllen. Eingabe der benötigten Netto-FTE-Bedarfe pro Tag. Eingabe der Jahresgehälter bzw. Stundenlöhne zum SOP, ggf. Zuschlägen (Bsp. Nachtschichtzuschläge) und Angabe, ob Brottofaktor aufgeschlagen werden soll oder nicht berücksichtigen. Ausgabe der durchschnittlichen und Gesamtlohnkosten über Laufzeit in der rechten Tabelle. Achtung: Detaillierte Berechnung der Personalkosten in separaten Tabellenblättern zur Vermeidung von Eingabefehlern.
A22: Step 4 | B22: Reiter "Sachkosten" mit CAPEX, OPEX und Kosten für Fremdleistungen befüllen. Eingabe CAPEX mit Einzelkosten über Laufzeit Eingabe OPEX mit Einzelkosten pro Monat Eingabe Kosten für Fremdleistungen mit Einzelkosten pro Jahr
A23: Step 5 | B23: Reiter "Summary" gibt die wichtigsten Projekt- und Kalkulationsdaten, Kosten und Umsätze als Zusammenfassung aus. Achtung: Keine Eingaben in diesem Reiter vornehmen! Detailanteile pro Kostengruppe können im unteren Bereich der Tabelle bei Bedarf ausgeklappt werden.
A24: Step 6 | B24: Reiter "OtO" dient als Kopiervorlage für die Befüllung des OtO-Formulars. Die Vertragsprüfung muss separat erfolgen.
A27: Hinweis / Disclaimer | B27: Dieses Kalkulationstool unterstützt bei der Projektkalkulation; alle Eingaben und Ergebnisse sind vom Anwender eigenverantwortlich auf Richtigkeit und Plausibilität zu prüfen. Für Funktionalität, Vollständigkeit oder Fehlerfreiheit – insbesondere nach Änderungen an Formeln oder Strukturen – wird keine Gewähr übernommen. Die Nutzung erfolgt auf eigenes Risiko.

Sheet B. Basisdaten
B1: Basisdaten | C1: Vertragsstart | F1: ='A. Start'!$E$3 -> 46492 | K1: To/p.a.
B3: Preiskalkulation | F3: Ermittlung der Ø produktiven Jahresstunden | J3: Personalnebenkosten | K3: Gehalts-empfänger | L3: Lohn-empfänger | O3: SV-Anteil Arbeitgeber | P3: 2026
B4: Gewinn | C4: 0.05 | F4: Personalkostensteigerung p.a. (Löhne & Gehälter) | G4: 0.03 | J4: 101 Soziallöhne (bezahlte Abwesenheit) | K4: n.v. | L4: =(G8+G11+G12+G13)/G14 -> 0.25480769 | O4: Krankenversicherung (AG-Anteil) | P4: =0.073+0.0145 -> 0.0875
B5: Risiko (Leadec Global C2 = 1,00%) | C5: 0.01 | J5: 102 Urlaubsgeld/ Prämie | K5: 0.02 | L5: 0.04 | O5: Rentenversicherung (AG-Anteil) | P5: 0.093
B6: Total | C6: =SUM(C4:C5) -> 0.06 | F6: Tage pro Jahr | G6: =DATE(YEAR('A. Start'!E3)+1,1,1)-DATE(YEAR('A. Start'!E3),1,1) -> 365 | J6: 102 Sonstige Zuschläge auf Basisgehalt/Tariflohn | K6: 0 | L6: 0.05 | O6: Arbeitslosenversicherung (AG-Anteil) | P6: 0.013
F7: Samstage/Sonntage | G7: 104 | O7: Pflegeversicherung (AG-Anteil) | P7: 0.018
B8: Konzern (HV) | C8: 0.05 | F8: Feiertage | G8: 9 | J8: 201 Sozialabgaben (SV-Anteil Arbeitgeber) | K8: 0.2436 | L8: 0.2436 | O8: Umlage U2 (U2 Mutterschutz | P8: 0.0056
B9: Umlagen für den Geschäftsbereich (BU) | C9: 0.025 | F9: Bruttoarbeitstage | G9: =G6-G7-G8 -> 252 | O9: Insolvenzgeldumlage | P9: 0.0015
B10: Umlagen für die Niederlassung (NL) | C10: 0.02 | J10: 601 Zuschlag für Sondertätigkeiten | K10: 0.2 | L10: 0.25 | O10: gesetzl. Unfallversicherung BG | P10: 0.01
B11: Total | C11: =SUM(C8:C10) -> 0.095 | F11: Urlaubstage | G11: 30 | O11: Schwerbehindert. Abgabe | P11: 0.01
F12: Krankheitstage | G12: 12 | J12: Berechnung Gehalts- und Lohnnebenkosten siehe I-1. und I-2. | P12: =SUM(P4:P11) -> 0.2386
B13: Verhandlungsmarge | C13: 0.06 | F13: Sonstiges/ Arbeitsfreistellung | G13: 2
B14: Total | C14: =SUM(C13) -> 0.06 | F14: Ø Anwesenheitstage FTE pro Jahr | G14: =G9-G11-G12-G13 -> 208
F16: Arbeitsstunden Lohnempfänger pro Tag [h] | G16: 8
F17: Ø produktive Jahresstunden [h] | G17: =G14*G16 -> 1664
F19: Arbeitsstunden Gehaltsemfänger pro Tag [h] | G19: 7.8
F20: Ø produktive Jahresstunden [h] | G20: =G14*G19 -> 1622.4

Sheet I-1. FTE-Gehälter
B1: I-1. Personalkosten Gehälter
H2: Projektlaufzeit
A3: Nr. | B3: Bezeichnung | C3: % | D3: Beispiel
A4: 000 | B4: Jahresgehalt [€/Jahr] im Startjahr | C4: Steigerung p.a. | D4: ='B. Basisdaten'!$G$4 -> 0.03 | H4: Years | I4: Months | J4: %-months
A5: 100 | B5: Jahresgehalt [€/Jahr] gemittelt Laufzeit | C5: 1 | D5: 45000 | H5: =YEAR('A. Start'!$E$3) -> 2027 | I5: =ROUNDDOWN(IF(AND($H5>=YEAR('A. Start'!$E$3),$H5<=YEAR('A. Start'!$E$4),YEAR('A. Start'!E3)<>YEAR('A. Start'!E4)),(DATEDIF(DATE(YEAR('A. Start'!$E$3),MONTH('A. Start'!$E$3),DAY('A. Start'!$E$3)),DATE($H5,12,31),"d")+1)/IF(MOD($H5,4)=0,366,365)*12,IF(YEAR('A. Start'!E3)=YEAR('A. Start'!E4),'A. Start'!E5,0)),1) -> 8.5 | J5: =I5/12 -> 0.70833333
A6: 101 | B6: - | C6: 0 | D6: 0 | H6: =IF(AND($H5<YEAR('A. Start'!$E$4),$H5>0),$H5+1,IF($H5=YEAR('A. Start'!$E$4),0,IF($H5=0,0,0))) -> 2028 | I6: =ROUNDUP(IF(AND($H6>=YEAR('A. Start'!$E$3),$H6<=YEAR('A. Start'!$E$4)),IF($H6<>YEAR('A. Start'!$E$4),12,(DATEDIF(DATE($H6,1,1),DATE(YEAR('A. Start'!$E$4),MONTH('A. Start'!$E$4),DAY('A. Start'!$E$4)),"d")+1)/IF(MOD($H6,4)=0,366,365)*12)),1) -> 12 | J6: =I6/12 -> 1
A7: 102 | B7: SV-Pflichtige Zuschläge (Prämien, Urlaubsgeld) | C7: ='B. Basisdaten'!$K$5+'B. Basisdaten'!$K$6 -> 0.02 | D7: =D5*($C$7) -> 900 | H7: =IF(AND($H6<YEAR('A. Start'!$E$4),$H6>0),$H6+1,IF($H6=YEAR('A. Start'!$E$4),0,IF($H6=0,0,0))) -> 2029 | I7: =ROUNDUP(IF(AND($H7>=YEAR('A. Start'!$E$3),$H7<=YEAR('A. Start'!$E$4)),IF($H7<>YEAR('A. Start'!$E$4),12,(DATEDIF(DATE($H7,1,1),DATE(YEAR('A. Start'!$E$4),MONTH('A. Start'!$E$4),DAY('A. Start'!$E$4)),"d")+1)/IF(MOD($H7,4)=0,366,365)*12)),1) -> 12 | J7: =I7/12 -> 1
A8: 200 | B8: Brutto-Arbeitnehmergehalt | C8: =SUM(C5:C7) -> 1.02 | D8: =(D7+D5)/$I$17 -> 28.29142 | H8: =IF(AND($H7<YEAR('A. Start'!$E$4),$H7>0),$H7+1,IF($H7=YEAR('A. Start'!$E$4),0,IF($H7=0,0,0))) -> 2030 | I8: =ROUNDUP(IF(AND($H8>=YEAR('A. Start'!$E$3),$H8<=YEAR('A. Start'!$E$4)),IF($H8<>YEAR('A. Start'!$E$4),12,(DATEDIF(DATE($H8,1,1),DATE(YEAR('A. Start'!$E$4),MONTH('A. Start'!$E$4),DAY('A. Start'!$E$4)),"d")+1)/IF(MOD($H8,4)=0,366,365)*12)),1) -> 12 | J8: =I8/12 -> 1
A9: 201 | B9: SV-Anteil AG | C9: ='B. Basisdaten'!K8 -> 0.2436 | D9: =(D8)*$C$9 -> 6.8917899 | H9: =IF(AND($H8<YEAR('A. Start'!$E$4),$H8>0),$H8+1,IF($H8=YEAR('A. Start'!$E$4),0,IF($H8=0,0,0))) -> 2031 | I9: =ROUNDUP(IF(AND($H9>=YEAR('A. Start'!$E$3),$H9<=YEAR('A. Start'!$E$4)),IF($H9<>YEAR('A. Start'!$E$4),12,(DATEDIF(DATE($H9,1,1),DATE(YEAR('A. Start'!$E$4),MONTH('A. Start'!$E$4),DAY('A. Start'!$E$4)),"d")+1)/IF(MOD($H9,4)=0,366,365)*12)),1) -> 12 | J9: =I9/12 -> 1
A10: 300 | B10: Kalkulatorisches Gehalt | C10: =C8*(1+C9) -> 1.268472 | D10: =D8+D9 -> 35.18321 | H10: =IF(AND($H9<YEAR('A. Start'!$E$4),$H9>0),$H9+1,IF($H9=YEAR('A. Start'!$E$4),0,IF($H9=0,0,0))) -> 2032 | I10: =ROUNDUP(IF(AND($H10>=YEAR('A. Start'!$E$3),$H10<=YEAR('A. Start'!$E$4)),IF($H10<>YEAR('A. Start'!$E$4),12,(DATEDIF(DATE($H10,1,1),DATE(YEAR('A. Start'!$E$4),MONTH('A. Start'!$E$4),DAY('A. Start'!$E$4)),"d")+1)/IF(MOD($H10,4)=0,366,365)*12)),1) -> 3.5 | J10: =I10/12 -> 0.29166667
A11: 301 | B11: Verwaltungsgemeinkostenzuschlag (HV/BU/NL-Umlagen) | C11: ='B. Basisdaten'!$C$11 -> 0.095 | D11: =(D10)/(1-$C$11-$C$13-$C$14)*$C$11 -> 3.9555088 | H11: =IF(AND($H10<YEAR('A. Start'!$E$4),$H10>0),$H10+1,IF($H10=YEAR('A. Start'!$E$4),0,IF($H10=0,0,0))) -> 0 | I11: =ROUNDUP(IF(AND($H11>=YEAR('A. Start'!$E$3),$H11<=YEAR('A. Start'!$E$4)),IF($H11<>YEAR('A. Start'!$E$4),12,(DATEDIF(DATE($H11,1,1),DATE(YEAR('A. Start'!$E$4),MONTH('A. Start'!$E$4),DAY('A. Start'!$E$4)),"d")+1)/IF(MOD($H11,4)=0,366,365)*12)),1) -> 0 | J11: =I11/12 -> 0
A12: 400 | B12: Selbstkosten-Stundenverrechnungssatz | C12: =D12/($D$5/$I$17) -> 1.4110813 | D12: =D10+D11 -> 39.138719 | H12: =IF(AND($H11<YEAR('A. Start'!$E$4),$H11>0),$H11+1,IF($H11=YEAR('A. Start'!$E$4),0,IF($H11=0,0,0))) -> 0 | I12: =ROUNDUP(IF(AND($H12>=YEAR('A. Start'!$E$3),$H12<=YEAR('A. Start'!$E$4)),IF($H12<>YEAR('A. Start'!$E$4),12,(DATEDIF(DATE($H12,1,1),DATE(YEAR('A. Start'!$E$4),MONTH('A. Start'!$E$4),DAY('A. Start'!$E$4)),"d")+1)/IF(MOD($H12,4)=0,366,365)*12)),1) -> 0 | J12: =I12/12 -> 0
A13: 401 | B13: Gewinn (%-Zuschlag auf SK-SVS) | C13: ='B. Basisdaten'!C4 -> 0.05 | D13: =(D10)/(1-$C$11-$C$13-$C$14)*($C$13+$C$14) -> 2.4982161 | H13: =IF(AND($H12<YEAR('A. Start'!$E$4),$H12>0),$H12+1,IF($H12=YEAR('A. Start'!$E$4),0,IF($H12=0,0,0))) -> 0 | I13: =ROUNDUP(IF(AND($H13>=YEAR('A. Start'!$E$3),$H13<=YEAR('A. Start'!$E$4)),IF($H13<>YEAR('A. Start'!$E$4),12,(DATEDIF(DATE($H13,1,1),DATE(YEAR('A. Start'!$E$4),MONTH('A. Start'!$E$4),DAY('A. Start'!$E$4)),"d")+1)/IF(MOD($H13,4)=0,366,365)*12)),1) -> 0 | J13: =I13/12 -> 0
A14: 402 | B14: + Risikozuschlag (%-Zuschlag auf SK-SVS) | C14: ='B. Basisdaten'!C5 -> 0.01 | H14: =IF(AND($H13<YEAR('A. Start'!$E$4),$H13>0),$H13+1,IF($H13=YEAR('A. Start'!$E$4),0,IF($H13=0,0,0))) -> 0 | I14: =ROUNDUP(IF(AND($H14>=YEAR('A. Start'!$E$3),$H14<=YEAR('A. Start'!$E$4)),IF($H14<>YEAR('A. Start'!$E$4),12,(DATEDIF(DATE($H14,1,1),DATE(YEAR('A. Start'!$E$4),MONTH('A. Start'!$E$4),DAY('A. Start'!$E$4)),"d")+1)/IF(MOD($H14,4)=0,366,365)*12)),1) -> 0 | J14: =I14/12 -> 0
A15: 500 | B15: Mitarbeiterverkaufsstundensatz ohne Verhandlung | C15: =D15/($D$5/$I$17) -> 1.5011503 | D15: =D13+D12 -> 41.636935 | I15: =ROUNDDOWN(SUM(I5:I14),0.5) -> 60 | J15: =I15/12 -> 5
A16: 501 | B16: Verhandlung (%-Zuschlag auf MA-VSVS) | C16: ='B. Basisdaten'!C13 -> 0.06 | D16: =(D15/(1-$C$16))-D15 -> 2.6576767
A17: 600 | B17: Mitarbeiterverkaufsstundensatz | C17: =D17/($D$5/$I$17) -> 1.5969684 | D17: =D15+D16 -> 44.294612 | H17: Prod. h/Jahr | I17: ='B. Basisdaten'!$G$20 -> 1622.4
A18: 601 | B18: Zuschlag für Sondertätigkeiten | C18: ='B. Basisdaten'!K10 -> 0.2 | D18: =D17*C18 -> 8.8589223
A19: 700 | B19: Mitarbeiterverkaufsstundensatz Sondertätigkeiten | C19: =D19/($D$5/$I$17) -> 1.9163621 | D19: =D18+D17 -> 53.153534
H20: Berechnung Gehaltskostensteigerung | R20: Übersicht Gehaltskosten pro Stunde | AF20: Berechnung kalkulatorischer Gesamt-Gehaltskosten
H21: {=TRANSPOSE(J5:J14)} -> 0.70833333 | I21: 1 | J21: 1 | K21: 1 | L21: 1 | M21: 0.29166667 | N21: 0 | O21: 0 | P21: 0 | Q21: 0
A22: Nr | B22: Qualifikation | C22: Ø-FTE/Tag netto | D22: 000-Jahresgehalt Jahr 1 | E22: FTE Brutto-Zuschlag [%] | F22: Brutto-FTE | H22: {=TRANSPOSE(H5:H14)} -> 2027 | I22: 2028 | J22: 2029 | K22: 2030 | L22: 2031 | M22: 2032 | N22: 0 | O22: 0 | P22: 0 | Q22: 0 | R22: 100 | S22: 101 102 | T22: 200 | U22: 201 | V22: 300 | W22: 301 | X22: 400 | Y22: 401 402 | Z22: 500 | AA22: 501 | AB22: 600 | AC22: 601 | AD22: 700 | AF22: Produktive Jahresstunden | AG22: 300-Kalkulatorische Gehaltskosten/Jahr | AH22: 300-Kalkulatorische Gehaltskosten/Laufzeit
A23: 1 | B23: Standortleitung | C23: 1 | D23: 98000 | E23: 0 | F23: =C23*(1+E23) -> 1 | H23: =D23 -> 98000 | I23: =IF(I$22=0,"",H23*(1+'B. Basisdaten'!$G$4)) -> 100940 | J23: =IF(J$22=0,"",I23*(1+'B. Basisdaten'!$G$4)) -> 103968.2 | K23: =IF(K$22=0,"",J23*(1+'B. Basisdaten'!$G$4)) -> 107087.25 | L23: =IF(L$22=0,"",K23*(1+'B. Basisdaten'!$G$4)) -> 110299.86 | M23: =IF(M$22=0,"",L23*(1+'B. Basisdaten'!$G$4)) -> 113608.86 | N23: =IF(N$22=0,"",M23*(1+'B. Basisdaten'!$G$4)) | O23: =IF(O$22=0,"",N23*(1+'B. Basisdaten'!$G$4)) | P23: =IF(P$22=0,"",O23*(1+'B. Basisdaten'!$G$4)) | Q23: =IF(Q$22=0,"",P23*(1+'B. Basisdaten'!$G$4)) | R23: =(SUMPRODUCT(H23:Q23,$H$21:$Q$21)/SUM($H$21:$Q$21))/'B. Basisdaten'!$G$20 -> 64.700184 | S23: =R23*($C$7) -> 1.2940037 | T23: =R23+S23 -> 65.994188 | U23: =(R23+S23)*$C$9 -> 16.076184 | V23: =T23+U23 -> 82.070372 | W23: =(R23+S23+U23)/(1-$C$11-$C$13-$C$14)*$C$11 -> 9.2268465 | X23: =V23+W23 -> 91.297218 | Y23: =(V23)/(1-$C$11-$C$13-$C$14)*($C$13+$C$14) -> 5.827482 | Z23: =X23+Y23 -> 97.1247 | AA23: =(Z23/(1-$C$16))-Z23 -> 6.199449 | AB23: =SUM(Z23)/(1-$C$16) -> 103.32415 | AC23: =AB23*$C$18 -> 20.66483 | AD23: =AC23+AB23 -> 123.98898 | AF23: ='B. Basisdaten'!$G$20*F23 -> 1622.4 | AG23: =AF23*V23 -> 133150.97 | AH23: =AG23*($I$15/12) -> 665754.86
A24: 2 | B24: Schichtleitung | C24: 2 | D24: 62000 | E24: 0.125 | F24: =C24*(1+E24) -> 2.25 | H24: =D24 -> 62000 | I24: =IF(I$22=0,"",H24*(1+'B. Basisdaten'!$G$4)) -> 63860 | J24: =IF(J$22=0,"",I24*(1+'B. Basisdaten'!$G$4)) -> 65775.8 | K24: =IF(K$22=0,"",J24*(1+'B. Basisdaten'!$G$4)) -> 67749.074 | L24: =IF(L$22=0,"",K24*(1+'B. Basisdaten'!$G$4)) -> 69781.546 | M24: =IF(M$22=0,"",L24*(1+'B. Basisdaten'!$G$4)) -> 71874.993 | N24: =IF(N$22=0,"",M24*(1+'B. Basisdaten'!$G$4)) | O24: =IF(O$22=0,"",N24*(1+'B. Basisdaten'!$G$4)) | P24: =IF(P$22=0,"",O24*(1+'B. Basisdaten'!$G$4)) | Q24: =IF(Q$22=0,"",P24*(1+'B. Basisdaten'!$G$4)) | R24: =(SUMPRODUCT(H24:Q24,$H$21:$Q$21)/SUM($H$21:$Q$21))/'B. Basisdaten'!$G$20 -> 40.93277 | S24: =R24*($C$7) -> 0.81865539 | T24: =R24+S24 -> 41.751425 | U24: =(R24+S24)*$C$9 -> 10.170647 | V24: =T24+U24 -> 51.922072 | W24: =(R24+S24+U24)/(1-$C$11-$C$13-$C$14)*$C$11 -> 5.8373927 | X24: =V24+W24 -> 57.759465 | Y24: =(V24)/(1-$C$11-$C$13-$C$14)*($C$13+$C$14) -> 3.6867743 | Z24: =X24+Y24 -> 61.446239 | AA24: =(Z24/(1-$C$16))-Z24 -> 3.9221004 | AB24: =SUM(Z24)/(1-$C$16) -> 65.368339 | AC24: =AB24*$C$18 -> 13.073668 | AD24: =AC24+AB24 -> 78.442007 | AF24: ='B. Basisdaten'!$G$20*F24 -> 3650.4 | AG24: =AF24*V24 -> 189536.33 | AH24: =AG24*($I$15/12) -> 947681.66
A25: 3 | B25: Disposition | C25: 1.5 | D25: 52000 | E25: 0.1 | F25: =C25*(1+E25) -> 1.65 | H25: =D25 -> 52000 | I25: =IF(I$22=0,"",H25*(1+'B. Basisdaten'!$G$4)) -> 53560 | J25: =IF(J$22=0,"",I25*(1+'B. Basisdaten'!$G$4)) -> 55166.8 | K25: =IF(K$22=0,"",J25*(1+'B. Basisdaten'!$G$4)) -> 56821.804 | L25: =IF(L$22=0,"",K25*(1+'B. Basisdaten'!$G$4)) -> 58526.458 | M25: =IF(M$22=0,"",L25*(1+'B. Basisdaten'!$G$4)) -> 60282.252 | N25: =IF(N$22=0,"",M25*(1+'B. Basisdaten'!$G$4)) | O25: =IF(O$22=0,"",N25*(1+'B. Basisdaten'!$G$4)) | P25: =IF(P$22=0,"",O25*(1+'B. Basisdaten'!$G$4)) | Q25: =IF(Q$22=0,"",P25*(1+'B. Basisdaten'!$G$4)) | R25: =(SUMPRODUCT(H25:Q25,$H$21:$Q$21)/SUM($H$21:$Q$21))/'B. Basisdaten'!$G$20 -> 34.33071 | S25: =R25*($C$7) -> 0.6866142 | T25: =R25+S25 -> 35.017324 | U25: =(R25+S25)*$C$9 -> 8.5302202 | V25: =T25+U25 -> 43.547544 | W25: =(R25+S25+U25)/(1-$C$11-$C$13-$C$14)*$C$11 -> 4.8958778 | X25: =V25+W25 -> 48.443422 | Y25: =(V25)/(1-$C$11-$C$13-$C$14)*($C$13+$C$14) -> 3.0921333 | Z25: =X25+Y25 -> 51.535555 | AA25: =(Z25/(1-$C$16))-Z25 -> 3.2895035 | AB25: =SUM(Z25)/(1-$C$16) -> 54.825059 | AC25: =AB25*$C$18 -> 10.965012 | AD25: =AC25+AB25 -> 65.790071 | AF25: ='B. Basisdaten'!$G$20*F25 -> 2676.96 | AG25: =AF25*V25 -> 116575.03 | AH25: =AG25*($I$15/12) -> 582875.17
A26: 4 | F26: =C26*(1+E26) -> 0 | H26: =D26 -> 0 | I26: =IF(I$22=0,"",H26*(1+'B. Basisdaten'!$G$4)) -> 0 | J26: =IF(J$22=0,"",I26*(1+'B. Basisdaten'!$G$4)) -> 0 | K26: =IF(K$22=0,"",J26*(1+'B. Basisdaten'!$G$4)) -> 0 | L26: =IF(L$22=0,"",K26*(1+'B. Basisdaten'!$G$4)) -> 0 | M26: =IF(M$22=0,"",L26*(1+'B. Basisdaten'!$G$4)) -> 0 | N26: =IF(N$22=0,"",M26*(1+'B. Basisdaten'!$G$4)) | O26: =IF(O$22=0,"",N26*(1+'B. Basisdaten'!$G$4)) | P26: =IF(P$22=0,"",O26*(1+'B. Basisdaten'!$G$4)) | Q26: =IF(Q$22=0,"",P26*(1+'B. Basisdaten'!$G$4)) | R26: =(SUMPRODUCT(H26:Q26,$H$21:$Q$21)/SUM($H$21:$Q$21))/'B. Basisdaten'!$G$20 -> 0 | S26: =R26*($C$7) -> 0 | T26: =R26+S26 -> 0 | U26: =(R26+S26)*$C$9 -> 0 | V26: =T26+U26 -> 0 | W26: =(R26+S26+U26)/(1-$C$11-$C$13-$C$14)*$C$11 -> 0 | X26: =V26+W26 -> 0 | Y26: =(V26)/(1-$C$11-$C$13-$C$14)*($C$13+$C$14) -> 0 | Z26: =X26+Y26 -> 0 | AA26: =(Z26/(1-$C$16))-Z26 -> 0 | AB26: =SUM(Z26)/(1-$C$16) -> 0 | AC26: =AB26*$C$18 -> 0 | AD26: =AC26+AB26 -> 0 | AF26: ='B. Basisdaten'!$G$20*F26 -> 0 | AG26: =AF26*V26 -> 0 | AH26: =AG26*($I$15/12) -> 0
A27: 5 | F27: =C27*(1+E27) -> 0 | H27: =D27 -> 0 | I27: =IF(I$22=0,"",H27*(1+'B. Basisdaten'!$G$4)) -> 0 | J27: =IF(J$22=0,"",I27*(1+'B. Basisdaten'!$G$4)) -> 0 | K27: =IF(K$22=0,"",J27*(1+'B. Basisdaten'!$G$4)) -> 0 | L27: =IF(L$22=0,"",K27*(1+'B. Basisdaten'!$G$4)) -> 0 | M27: =IF(M$22=0,"",L27*(1+'B. Basisdaten'!$G$4)) -> 0 | N27: =IF(N$22=0,"",M27*(1+'B. Basisdaten'!$G$4)) | O27: =IF(O$22=0,"",N27*(1+'B. Basisdaten'!$G$4)) | P27: =IF(P$22=0,"",O27*(1+'B. Basisdaten'!$G$4)) | Q27: =IF(Q$22=0,"",P27*(1+'B. Basisdaten'!$G$4)) | R27: =(SUMPRODUCT(H27:Q27,$H$21:$Q$21)/SUM($H$21:$Q$21))/'B. Basisdaten'!$G$20 -> 0 | S27: =R27*($C$7) -> 0 | T27: =R27+S27 -> 0 | U27: =(R27+S27)*$C$9 -> 0 | V27: =T27+U27 -> 0 | W27: =(R27+S27+U27)/(1-$C$11-$C$13-$C$14)*$C$11 -> 0 | X27: =V27+W27 -> 0 | Y27: =(V27)/(1-$C$11-$C$13-$C$14)*($C$13+$C$14) -> 0 | Z27: =X27+Y27 -> 0 | AA27: =(Z27/(1-$C$16))-Z27 -> 0 | AB27: =SUM(Z27)/(1-$C$16) -> 0 | AC27: =AB27*$C$18 -> 0 | AD27: =AC27+AB27 -> 0 | AF27: ='B. Basisdaten'!$G$20*F27 -> 0 | AG27: =AF27*V27 -> 0 | AH27: =AG27*($I$15/12) -> 0
A28: 6 | F28: =C28*(1+E28) -> 0 | H28: =D28 -> 0 | I28: =IF(I$22=0,"",H28*(1+'B. Basisdaten'!$G$4)) -> 0 | J28: =IF(J$22=0,"",I28*(1+'B. Basisdaten'!$G$4)) -> 0 | K28: =IF(K$22=0,"",J28*(1+'B. Basisdaten'!$G$4)) -> 0 | L28: =IF(L$22=0,"",K28*(1+'B. Basisdaten'!$G$4)) -> 0 | M28: =IF(M$22=0,"",L28*(1+'B. Basisdaten'!$G$4)) -> 0 | N28: =IF(N$22=0,"",M28*(1+'B. Basisdaten'!$G$4)) | O28: =IF(O$22=0,"",N28*(1+'B. Basisdaten'!$G$4)) | P28: =IF(P$22=0,"",O28*(1+'B. Basisdaten'!$G$4)) | Q28: =IF(Q$22=0,"",P28*(1+'B. Basisdaten'!$G$4)) | R28: =(SUMPRODUCT(H28:Q28,$H$21:$Q$21)/SUM($H$21:$Q$21))/'B. Basisdaten'!$G$20 -> 0 | S28: =R28*($C$7) -> 0 | T28: =R28+S28 -> 0 | U28: =(R28+S28)*$C$9 -> 0 | V28: =T28+U28 -> 0 | W28: =(R28+S28+U28)/(1-$C$11-$C$13-$C$14)*$C$11 -> 0 | X28: =V28+W28 -> 0 | Y28: =(V28)/(1-$C$11-$C$13-$C$14)*($C$13+$C$14) -> 0 | Z28: =X28+Y28 -> 0 | AA28: =(Z28/(1-$C$16))-Z28 -> 0 | AB28: =SUM(Z28)/(1-$C$16) -> 0 | AC28: =AB28*$C$18 -> 0 | AD28: =AC28+AB28 -> 0 | AF28: ='B. Basisdaten'!$G$20*F28 -> 0 | AG28: =AF28*V28 -> 0 | AH28: =AG28*($I$15/12) -> 0
A29: 7 | F29: =C29*(1+E29) -> 0 | H29: =D29 -> 0 | I29: =IF(I$22=0,"",H29*(1+'B. Basisdaten'!$G$4)) -> 0 | J29: =IF(J$22=0,"",I29*(1+'B. Basisdaten'!$G$4)) -> 0 | K29: =IF(K$22=0,"",J29*(1+'B. Basisdaten'!$G$4)) -> 0 | L29: =IF(L$22=0,"",K29*(1+'B. Basisdaten'!$G$4)) -> 0 | M29: =IF(M$22=0,"",L29*(1+'B. Basisdaten'!$G$4)) -> 0 | N29: =IF(N$22=0,"",M29*(1+'B. Basisdaten'!$G$4)) | O29: =IF(O$22=0,"",N29*(1+'B. Basisdaten'!$G$4)) | P29: =IF(P$22=0,"",O29*(1+'B. Basisdaten'!$G$4)) | Q29: =IF(Q$22=0,"",P29*(1+'B. Basisdaten'!$G$4)) | R29: =(SUMPRODUCT(H29:Q29,$H$21:$Q$21)/SUM($H$21:$Q$21))/'B. Basisdaten'!$G$20 -> 0 | S29: =R29*($C$7) -> 0 | T29: =R29+S29 -> 0 | U29: =(R29+S29)*$C$9 -> 0 | V29: =T29+U29 -> 0 | W29: =(R29+S29+U29)/(1-$C$11-$C$13-$C$14)*$C$11 -> 0 | X29: =V29+W29 -> 0 | Y29: =(V29)/(1-$C$11-$C$13-$C$14)*($C$13+$C$14) -> 0 | Z29: =X29+Y29 -> 0 | AA29: =(Z29/(1-$C$16))-Z29 -> 0 | AB29: =SUM(Z29)/(1-$C$16) -> 0 | AC29: =AB29*$C$18 -> 0 | AD29: =AC29+AB29 -> 0 | AF29: ='B. Basisdaten'!$G$20*F29 -> 0 | AG29: =AF29*V29 -> 0 | AH29: =AG29*($I$15/12) -> 0
A30: 8 | F30: =C30*(1+E30) -> 0 | H30: =D30 -> 0 | I30: =IF(I$22=0,"",H30*(1+'B. Basisdaten'!$G$4)) -> 0 | J30: =IF(J$22=0,"",I30*(1+'B. Basisdaten'!$G$4)) -> 0 | K30: =IF(K$22=0,"",J30*(1+'B. Basisdaten'!$G$4)) -> 0 | L30: =IF(L$22=0,"",K30*(1+'B. Basisdaten'!$G$4)) -> 0 | M30: =IF(M$22=0,"",L30*(1+'B. Basisdaten'!$G$4)) -> 0 | N30: =IF(N$22=0,"",M30*(1+'B. Basisdaten'!$G$4)) | O30: =IF(O$22=0,"",N30*(1+'B. Basisdaten'!$G$4)) | P30: =IF(P$22=0,"",O30*(1+'B. Basisdaten'!$G$4)) | Q30: =IF(Q$22=0,"",P30*(1+'B. Basisdaten'!$G$4)) | R30: =(SUMPRODUCT(H30:Q30,$H$21:$Q$21)/SUM($H$21:$Q$21))/'B. Basisdaten'!$G$20 -> 0 | S30: =R30*($C$7) -> 0 | T30: =R30+S30 -> 0 | U30: =(R30+S30)*$C$9 -> 0 | V30: =T30+U30 -> 0 | W30: =(R30+S30+U30)/(1-$C$11-$C$13-$C$14)*$C$11 -> 0 | X30: =V30+W30 -> 0 | Y30: =(V30)/(1-$C$11-$C$13-$C$14)*($C$13+$C$14) -> 0 | Z30: =X30+Y30 -> 0 | AA30: =(Z30/(1-$C$16))-Z30 -> 0 | AB30: =SUM(Z30)/(1-$C$16) -> 0 | AC30: =AB30*$C$18 -> 0 | AD30: =AC30+AB30 -> 0 | AF30: ='B. Basisdaten'!$G$20*F30 -> 0 | AG30: =AF30*V30 -> 0 | AH30: =AG30*($I$15/12) -> 0
A31: 9 | F31: =C31*(1+E31) -> 0 | H31: =D31 -> 0 | I31: =IF(I$22=0,"",H31*(1+'B. Basisdaten'!$G$4)) -> 0 | J31: =IF(J$22=0,"",I31*(1+'B. Basisdaten'!$G$4)) -> 0 | K31: =IF(K$22=0,"",J31*(1+'B. Basisdaten'!$G$4)) -> 0 | L31: =IF(L$22=0,"",K31*(1+'B. Basisdaten'!$G$4)) -> 0 | M31: =IF(M$22=0,"",L31*(1+'B. Basisdaten'!$G$4)) -> 0 | N31: =IF(N$22=0,"",M31*(1+'B. Basisdaten'!$G$4)) | O31: =IF(O$22=0,"",N31*(1+'B. Basisdaten'!$G$4)) | P31: =IF(P$22=0,"",O31*(1+'B. Basisdaten'!$G$4)) | Q31: =IF(Q$22=0,"",P31*(1+'B. Basisdaten'!$G$4)) | R31: =(SUMPRODUCT(H31:Q31,$H$21:$Q$21)/SUM($H$21:$Q$21))/'B. Basisdaten'!$G$20 -> 0 | S31: =R31*($C$7) -> 0 | T31: =R31+S31 -> 0 | U31: =(R31+S31)*$C$9 -> 0 | V31: =T31+U31 -> 0 | W31: =(R31+S31+U31)/(1-$C$11-$C$13-$C$14)*$C$11 -> 0 | X31: =V31+W31 -> 0 | Y31: =(V31)/(1-$C$11-$C$13-$C$14)*($C$13+$C$14) -> 0 | Z31: =X31+Y31 -> 0 | AA31: =(Z31/(1-$C$16))-Z31 -> 0 | AB31: =SUM(Z31)/(1-$C$16) -> 0 | AC31: =AB31*$C$18 -> 0 | AD31: =AC31+AB31 -> 0 | AF31: ='B. Basisdaten'!$G$20*F31 -> 0 | AG31: =AF31*V31 -> 0 | AH31: =AG31*($I$15/12) -> 0
A32: 10 | F32: =C32*(1+E32) -> 0 | H32: =D32 -> 0 | I32: =IF(I$22=0,"",H32*(1+'B. Basisdaten'!$G$4)) -> 0 | J32: =IF(J$22=0,"",I32*(1+'B. Basisdaten'!$G$4)) -> 0 | K32: =IF(K$22=0,"",J32*(1+'B. Basisdaten'!$G$4)) -> 0 | L32: =IF(L$22=0,"",K32*(1+'B. Basisdaten'!$G$4)) -> 0 | M32: =IF(M$22=0,"",L32*(1+'B. Basisdaten'!$G$4)) -> 0 | N32: =IF(N$22=0,"",M32*(1+'B. Basisdaten'!$G$4)) | O32: =IF(O$22=0,"",N32*(1+'B. Basisdaten'!$G$4)) | P32: =IF(P$22=0,"",O32*(1+'B. Basisdaten'!$G$4)) | Q32: =IF(Q$22=0,"",P32*(1+'B. Basisdaten'!$G$4)) | R32: =(SUMPRODUCT(H32:Q32,$H$21:$Q$21)/SUM($H$21:$Q$21))/'B. Basisdaten'!$G$20 -> 0 | S32: =R32*($C$7) -> 0 | T32: =R32+S32 -> 0 | U32: =(R32+S32)*$C$9 -> 0 | V32: =T32+U32 -> 0 | W32: =(R32+S32+U32)/(1-$C$11-$C$13-$C$14)*$C$11 -> 0 | X32: =V32+W32 -> 0 | Y32: =(V32)/(1-$C$11-$C$13-$C$14)*($C$13+$C$14) -> 0 | Z32: =X32+Y32 -> 0 | AA32: =(Z32/(1-$C$16))-Z32 -> 0 | AB32: =SUM(Z32)/(1-$C$16) -> 0 | AC32: =AB32*$C$18 -> 0 | AD32: =AC32+AB32 -> 0 | AF32: ='B. Basisdaten'!$G$20*F32 -> 0 | AG32: =AF32*V32 -> 0 | AH32: =AG32*($I$15/12) -> 0
A33: # | B33: Total | C33: =SUM(C23:C32) -> 4.5 | F33: =SUM(F23:F32) -> 4.9 | AF33: =SUM(AF23:AF32) -> 7949.76 | AG33: =SUM(AG23:AG32) -> 439262.34 | AH33: =SUM(AH23:AH32) -> 2196311.7
AH35: 2382312.9
AH36: =AH33/AH35-1 -> -0.078075887

Sheet I-2. FTE-Löhne
B1: I-2. Personalkosten Löhne
H2: Projektlaufzeit
A3: Nr. | B3: Bezeichnung | C3: % | D3: Beispiel
A4: 000 | B4: Tariflicher Grundlohn[€/h] im Startjahr | C4: Steigerung p.a. | D4: ='B. Basisdaten'!$G$4 -> 0.03 | H4: Years | I4: Months | J4: %-months
A5: 100 | B5: Tariflicher Grundlohn [€/h] gemittelt Laufzeit | C5: 1 | D5: 1 | H5: =YEAR('A. Start'!$E$3) -> 2027 | I5: =ROUNDDOWN(IF(AND($H5>=YEAR('A. Start'!$E$3),$H5<=YEAR('A. Start'!$E$4),YEAR('A. Start'!E3)<>YEAR('A. Start'!E4)),(DATEDIF(DATE(YEAR('A. Start'!$E$3),MONTH('A. Start'!$E$3),DAY('A. Start'!$E$3)),DATE($H5,12,31),"d")+1)/IF(MOD($H5,4)=0,366,365)*12,IF(YEAR('A. Start'!E3)=YEAR('A. Start'!E4),'A. Start'!E5,0)),1) -> 8.5 | J5: =I5/12 -> 0.70833333
A6: 101 | B6: Soziallöhne (bezahlte Abwesenheit) | C6: =SUM('B. Basisdaten'!$G$8,'B. Basisdaten'!$G$11:$G$13)/'B. Basisdaten'!$G$14 -> 0.25480769 | D6: =D5*($C$6+$C$7) -> 0.34480769 | H6: =IF(AND($H5<YEAR('A. Start'!$E$4),$H5>0),$H5+1,IF($H5=YEAR('A. Start'!$E$4),0,IF($H5=0,0,0))) -> 2028 | I6: =ROUNDUP(IF(AND($H6>=YEAR('A. Start'!$E$3),$H6<=YEAR('A. Start'!$E$4)),IF($H6<>YEAR('A. Start'!$E$4),12,(DATEDIF(DATE($H6,1,1),DATE(YEAR('A. Start'!$E$4),MONTH('A. Start'!$E$4),DAY('A. Start'!$E$4)),"d")+1)/IF(MOD($H6,4)=0,366,365)*12)),1) -> 12 | J6: =I6/12 -> 1
A7: 102 | B7: SV-Pflichtige Zuschläge (Schicht, Prämien, Urlaub) | C7: ='B. Basisdaten'!$L$5+'B. Basisdaten'!$L$6 -> 0.09 | H7: =IF(AND($H6<YEAR('A. Start'!$E$4),$H6>0),$H6+1,IF($H6=YEAR('A. Start'!$E$4),0,IF($H6=0,0,0))) -> 2029 | I7: =ROUNDUP(IF(AND($H7>=YEAR('A. Start'!$E$3),$H7<=YEAR('A. Start'!$E$4)),IF($H7<>YEAR('A. Start'!$E$4),12,(DATEDIF(DATE($H7,1,1),DATE(YEAR('A. Start'!$E$4),MONTH('A. Start'!$E$4),DAY('A. Start'!$E$4)),"d")+1)/IF(MOD($H7,4)=0,366,365)*12)),1) -> 12 | J7: =I7/12 -> 1
A8: 200 | B8: Brutto-Arbeitnehmerlohn | C8: =SUM(C5:C7) -> 1.3448077 | D8: =D6+D5 -> 1.3448077 | H8: =IF(AND($H7<YEAR('A. Start'!$E$4),$H7>0),$H7+1,IF($H7=YEAR('A. Start'!$E$4),0,IF($H7=0,0,0))) -> 2030 | I8: =ROUNDUP(IF(AND($H8>=YEAR('A. Start'!$E$3),$H8<=YEAR('A. Start'!$E$4)),IF($H8<>YEAR('A. Start'!$E$4),12,(DATEDIF(DATE($H8,1,1),DATE(YEAR('A. Start'!$E$4),MONTH('A. Start'!$E$4),DAY('A. Start'!$E$4)),"d")+1)/IF(MOD($H8,4)=0,366,365)*12)),1) -> 12 | J8: =I8/12 -> 1
A9: 201 | B9: SV-Anteil AG | C9: ='B. Basisdaten'!L8 -> 0.2436 | D9: =(D5+D6)*$C$9 -> 0.32759515 | H9: =IF(AND($H8<YEAR('A. Start'!$E$4),$H8>0),$H8+1,IF($H8=YEAR('A. Start'!$E$4),0,IF($H8=0,0,0))) -> 2031 | I9: =ROUNDUP(IF(AND($H9>=YEAR('A. Start'!$E$3),$H9<=YEAR('A. Start'!$E$4)),IF($H9<>YEAR('A. Start'!$E$4),12,(DATEDIF(DATE($H9,1,1),DATE(YEAR('A. Start'!$E$4),MONTH('A. Start'!$E$4),DAY('A. Start'!$E$4)),"d")+1)/IF(MOD($H9,4)=0,366,365)*12)),1) -> 12 | J9: =I9/12 -> 1
A10: 300 | B10: Kalkulatorischer Lohn | C10: =C8*(1+C9) -> 1.6724028 | D10: =D8+D9 -> 1.6724028 | H10: =IF(AND($H9<YEAR('A. Start'!$E$4),$H9>0),$H9+1,IF($H9=YEAR('A. Start'!$E$4),0,IF($H9=0,0,0))) -> 2032 | I10: =ROUNDUP(IF(AND($H10>=YEAR('A. Start'!$E$3),$H10<=YEAR('A. Start'!$E$4)),IF($H10<>YEAR('A. Start'!$E$4),12,(DATEDIF(DATE($H10,1,1),DATE(YEAR('A. Start'!$E$4),MONTH('A. Start'!$E$4),DAY('A. Start'!$E$4)),"d")+1)/IF(MOD($H10,4)=0,366,365)*12)),1) -> 3.5 | J10: =I10/12 -> 0.29166667
A11: 301 | B11: Verwaltungsgemeinkostenzuschlag (HV/BU/NL-Umlagen) | C11: ='B. Basisdaten'!$C$11 -> 0.095 | D11: =(D10)/(1-$C$11-$C$13-$C$14)*$C$11 -> 0.18802162 | H11: =IF(AND($H10<YEAR('A. Start'!$E$4),$H10>0),$H10+1,IF($H10=YEAR('A. Start'!$E$4),0,IF($H10=0,0,0))) -> 0 | I11: =ROUNDUP(IF(AND($H11>=YEAR('A. Start'!$E$3),$H11<=YEAR('A. Start'!$E$4)),IF($H11<>YEAR('A. Start'!$E$4),12,(DATEDIF(DATE($H11,1,1),DATE(YEAR('A. Start'!$E$4),MONTH('A. Start'!$E$4),DAY('A. Start'!$E$4)),"d")+1)/IF(MOD($H11,4)=0,366,365)*12)),1) -> 0 | J11: =I11/12 -> 0
A12: 400 | B12: Selbstkosten-Stundenverrechnungssatz | C12: =D12/D5 -> 1.8604245 | D12: =D10+D11 -> 1.8604245 | H12: =IF(AND($H11<YEAR('A. Start'!$E$4),$H11>0),$H11+1,IF($H11=YEAR('A. Start'!$E$4),0,IF($H11=0,0,0))) -> 0 | I12: =ROUNDUP(IF(AND($H12>=YEAR('A. Start'!$E$3),$H12<=YEAR('A. Start'!$E$4)),IF($H12<>YEAR('A. Start'!$E$4),12,(DATEDIF(DATE($H12,1,1),DATE(YEAR('A. Start'!$E$4),MONTH('A. Start'!$E$4),DAY('A. Start'!$E$4)),"d")+1)/IF(MOD($H12,4)=0,366,365)*12)),1) -> 0 | J12: =I12/12 -> 0
A13: 401 | B13: Gewinn (%-Zuschlag auf SK-SVS) | C13: ='B. Basisdaten'!C4 -> 0.05 | D13: =(D10)/(1-$C$11-$C$13-$C$14)*($C$13+$C$14) -> 0.1187505 | H13: =IF(AND($H12<YEAR('A. Start'!$E$4),$H12>0),$H12+1,IF($H12=YEAR('A. Start'!$E$4),0,IF($H12=0,0,0))) -> 0 | I13: =ROUNDUP(IF(AND($H13>=YEAR('A. Start'!$E$3),$H13<=YEAR('A. Start'!$E$4)),IF($H13<>YEAR('A. Start'!$E$4),12,(DATEDIF(DATE($H13,1,1),DATE(YEAR('A. Start'!$E$4),MONTH('A. Start'!$E$4),DAY('A. Start'!$E$4)),"d")+1)/IF(MOD($H13,4)=0,366,365)*12)),1) -> 0 | J13: =I13/12 -> 0
A14: 402 | B14: + Risikozuschlag (%-Zuschlag auf SK-SVS) | C14: ='B. Basisdaten'!C5 -> 0.01 | H14: =IF(AND($H13<YEAR('A. Start'!$E$4),$H13>0),$H13+1,IF($H13=YEAR('A. Start'!$E$4),0,IF($H13=0,0,0))) -> 0 | I14: =ROUNDUP(IF(AND($H14>=YEAR('A. Start'!$E$3),$H14<=YEAR('A. Start'!$E$4)),IF($H14<>YEAR('A. Start'!$E$4),12,(DATEDIF(DATE($H14,1,1),DATE(YEAR('A. Start'!$E$4),MONTH('A. Start'!$E$4),DAY('A. Start'!$E$4)),"d")+1)/IF(MOD($H14,4)=0,366,365)*12)),1) -> 0 | J14: =I14/12 -> 0
A15: 500 | B15: Mitarbeiterverkaufsstundensatz ohne Verhandlung | C15: =D15/D5 -> 1.979175 | D15: =D13+D12 -> 1.979175 | I15: =ROUNDDOWN(SUM(I5:I14),0.5) -> 60 | J15: =I15/12 -> 5
A16: 501 | B16: Verhandlung (%-Zuschlag auf MA-VSVS) | C16: ='B. Basisdaten'!C13 -> 0.06 | D16: =(D15/(1-$C$16))-D15 -> 0.12633032
A17: 600 | B17: Mitarbeiterverkaufsstundensatz | C17: =D17/D5 -> 2.1055053 | D17: =D15+D16 -> 2.1055053 | H17: Prod. h/Jahr | I17: ='B. Basisdaten'!$G$17 -> 1664
A18: 601 | B18: Zuschlag für Sondertätigkeiten | C18: ='B. Basisdaten'!$L$10 -> 0.25 | D18: =D17*C18 -> 0.52637632
A19: 700 | B19: Mitarbeiterverkaufsstundensatz Sondertätigkeiten | C19: =D19/D5 -> 2.6318816 | D19: =D18+D17 -> 2.6318816
H20: Berechnung Lohnkostensteigerung | R20: Übersicht Lohnkosten pro Stunde | AF20: Berechnung kalkulatorischer Gesamt-Lohnkosten
H21: {=TRANSPOSE(J5:J14)} -> 0.70833333 | I21: 1 | J21: 1 | K21: 1 | L21: 1 | M21: 0.29166667 | N21: 0 | O21: 0 | P21: 0 | Q21: 0
A22: Nr | B22: Qualifikation | C22: Ø-FTE/Tag netto | D22: 000-Tarif. Grundlohn Jahr 1 | E22: FTE Brutto-Zuschlag [%] | F22: Brutto-FTE | H22: {=TRANSPOSE(H5:H14)} -> 2027 | I22: 2028 | J22: 2029 | K22: 2030 | L22: 2031 | M22: 2032 | N22: 0 | O22: 0 | P22: 0 | Q22: 0 | R22: 100 | S22: 101 102 | T22: 200 | U22: 201 | V22: 300 | W22: 301 | X22: 400 | Y22: 401 402 | Z22: 500 | AA22: 501 | AB22: 600 | AC22: 601 | AD22: 700 | AF22: Produktive Jahresstunden | AG22: 300-Kalkulatorische Lohnkosten/Jahr | AH22: 300-Kalkulatorische Lohnkosten/Laufzeit
A23: 1 | B23: Lagerist | C23: 11.8625 | D23: 17.9 | E23: 0.1776 | F23: =C23*(1+E23) -> 13.96928 | H23: =D23 -> 17.9 | I23: =IF(I$22=0,"",H23*(1+'B. Basisdaten'!$G$4)) -> 18.437 | J23: =IF(J$22=0,"",I23*(1+'B. Basisdaten'!$G$4)) -> 18.99011 | K23: =IF(K$22=0,"",J23*(1+'B. Basisdaten'!$G$4)) -> 19.559813 | L23: =IF(L$22=0,"",K23*(1+'B. Basisdaten'!$G$4)) -> 20.146608 | M23: =IF(M$22=0,"",L23*(1+'B. Basisdaten'!$G$4)) -> 20.751006 | N23: =IF(N$22=0,"",M23*(1+'B. Basisdaten'!$G$4)) | O23: =IF(O$22=0,"",N23*(1+'B. Basisdaten'!$G$4)) | P23: =IF(P$22=0,"",O23*(1+'B. Basisdaten'!$G$4)) | Q23: =IF(Q$22=0,"",P23*(1+'B. Basisdaten'!$G$4)) | R23: =SUMPRODUCT(H23:Q23,$H$21:$Q$21)/SUM($H$21:$Q$21) -> 19.173015 | S23: =R23*($C$6+$C$7) -> 6.611003 | T23: =R23+S23 -> 25.784018 | U23: =(R23+S23)*$C$9 -> 6.2809868 | V23: =T23+U23 -> 32.065005 | W23: =(R23+S23+U23)/(1-$C$11-$C$13-$C$14)*$C$11 -> 3.6049414 | X23: =V23+W23 -> 35.669946 | Y23: =(V23)/(1-$C$11-$C$13-$C$14)*($C$13+$C$14) -> 2.2768051 | Z23: =X23+Y23 -> 37.946751 | AA23: =(Z23/(1-$C$16))-Z23 -> 2.422133 | AB23: =SUM(Z23)/(1-$C$16) -> 40.368884 | AC23: =AB23*$C$18 -> 10.092221 | AD23: =AB23+AC23 -> 50.461105 | AF23: ='B. Basisdaten'!$G$17*F23 -> 23244.882 | AG23: =AF23*V23 -> 745347.25 | AH23: =AG23*($I$15/12) -> 3726736.2
A24: 2 | B24: Staplerfahrer | C24: 6.3 | D24: 18.9 | E24: 0.1776 | F24: =C24*(1+E24) -> 7.41888 | H24: =D24 -> 18.9 | I24: =IF(I$22=0,"",H24*(1+'B. Basisdaten'!$G$4)) -> 19.467 | J24: =IF(J$22=0,"",I24*(1+'B. Basisdaten'!$G$4)) -> 20.05101 | K24: =IF(K$22=0,"",J24*(1+'B. Basisdaten'!$G$4)) -> 20.65254 | L24: =IF(L$22=0,"",K24*(1+'B. Basisdaten'!$G$4)) -> 21.272117 | M24: =IF(M$22=0,"",L24*(1+'B. Basisdaten'!$G$4)) -> 21.91028 | N24: =IF(N$22=0,"",M24*(1+'B. Basisdaten'!$G$4)) | O24: =IF(O$22=0,"",N24*(1+'B. Basisdaten'!$G$4)) | P24: =IF(P$22=0,"",O24*(1+'B. Basisdaten'!$G$4)) | Q24: =IF(Q$22=0,"",P24*(1+'B. Basisdaten'!$G$4)) | R24: =SUMPRODUCT(H24:Q24,$H$21:$Q$21)/SUM($H$21:$Q$21) -> 20.244133 | S24: =R24*($C$6+$C$7) -> 6.9803328 | T24: =R24+S24 -> 27.224466 | U24: =(R24+S24)*$C$9 -> 6.6318799 | V24: =T24+U24 -> 33.856346 | W24: =(R24+S24+U24)/(1-$C$11-$C$13-$C$14)*$C$11 -> 3.8063347 | X24: =V24+W24 -> 37.66268 | Y24: =(V24)/(1-$C$11-$C$13-$C$14)*($C$13+$C$14) -> 2.4040009 | Z24: =X24+Y24 -> 40.066681 | AA24: =(Z24/(1-$C$16))-Z24 -> 2.5574477 | AB24: =SUM(Z24)/(1-$C$16) -> 42.624129 | AC24: =AB24*$C$18 -> 10.656032 | AD24: =AB24+AC24 -> 53.280161 | AF24: ='B. Basisdaten'!$G$17*F24 -> 12345.016 | AG24: =AF24*V24 -> 417957.14 | AH24: =AG24*($I$15/12) -> 2089785.7
A25: 3 | B25: Kommissionierer (Aushilfe) | C25: 0 | D25: 16.5 | E25: 0 | F25: =C25*(1+E25) -> 0 | H25: =D25 -> 16.5 | I25: =IF(I$22=0,"",H25*(1+'B. Basisdaten'!$G$4)) -> 16.995 | J25: =IF(J$22=0,"",I25*(1+'B. Basisdaten'!$G$4)) -> 17.50485 | K25: =IF(K$22=0,"",J25*(1+'B. Basisdaten'!$G$4)) -> 18.029995 | L25: =IF(L$22=0,"",K25*(1+'B. Basisdaten'!$G$4)) -> 18.570895 | M25: =IF(M$22=0,"",L25*(1+'B. Basisdaten'!$G$4)) -> 19.128022 | N25: =IF(N$22=0,"",M25*(1+'B. Basisdaten'!$G$4)) | O25: =IF(O$22=0,"",N25*(1+'B. Basisdaten'!$G$4)) | P25: =IF(P$22=0,"",O25*(1+'B. Basisdaten'!$G$4)) | Q25: =IF(Q$22=0,"",P25*(1+'B. Basisdaten'!$G$4)) | R25: =SUMPRODUCT(H25:Q25,$H$21:$Q$21)/SUM($H$21:$Q$21) -> 17.673449 | S25: =R25*($C$6+$C$7) -> 6.0939413 | T25: =R25+S25 -> 23.767391 | U25: =(R25+S25)*$C$9 -> 5.7897364 | V25: =T25+U25 -> 29.557127 | W25: =(R25+S25+U25)/(1-$C$11-$C$13-$C$14)*$C$11 -> 3.3229906 | X25: =V25+W25 -> 32.880118 | Y25: =(V25)/(1-$C$11-$C$13-$C$14)*($C$13+$C$14) -> 2.0987309 | Z25: =X25+Y25 -> 34.978849 | AA25: =(Z25/(1-$C$16))-Z25 -> 2.2326925 | AB25: =SUM(Z25)/(1-$C$16) -> 37.211541 | AC25: =AB25*$C$18 -> 9.3028853 | AD25: =AB25+AC25 -> 46.514427 | AF25: ='B. Basisdaten'!$G$17*F25 -> 0 | AG25: =AF25*V25 -> 0 | AH25: =AG25*($I$15/12) -> 0
A26: 4 | F26: =C26*(1+E26) -> 0 | H26: =D26 -> 0 | I26: =IF(I$22=0,"",H26*(1+'B. Basisdaten'!$G$4)) -> 0 | J26: =IF(J$22=0,"",I26*(1+'B. Basisdaten'!$G$4)) -> 0 | K26: =IF(K$22=0,"",J26*(1+'B. Basisdaten'!$G$4)) -> 0 | L26: =IF(L$22=0,"",K26*(1+'B. Basisdaten'!$G$4)) -> 0 | M26: =IF(M$22=0,"",L26*(1+'B. Basisdaten'!$G$4)) -> 0 | N26: =IF(N$22=0,"",M26*(1+'B. Basisdaten'!$G$4)) | O26: =IF(O$22=0,"",N26*(1+'B. Basisdaten'!$G$4)) | P26: =IF(P$22=0,"",O26*(1+'B. Basisdaten'!$G$4)) | Q26: =IF(Q$22=0,"",P26*(1+'B. Basisdaten'!$G$4)) | R26: =SUMPRODUCT(H26:Q26,$H$21:$Q$21)/SUM($H$21:$Q$21) -> 0 | S26: =R26*($C$6+$C$7) -> 0 | T26: =R26+S26 -> 0 | U26: =(R26+S26)*$C$9 -> 0 | V26: =T26+U26 -> 0 | W26: =(R26+S26+U26)/(1-$C$11-$C$13-$C$14)*$C$11 -> 0 | X26: =V26+W26 -> 0 | Y26: =(V26)/(1-$C$11-$C$13-$C$14)*($C$13+$C$14) -> 0 | Z26: =X26+Y26 -> 0 | AA26: =(Z26/(1-$C$16))-Z26 -> 0 | AB26: =SUM(Z26)/(1-$C$16) -> 0 | AC26: =AB26*$C$18 -> 0 | AD26: =AB26+AC26 -> 0 | AF26: ='B. Basisdaten'!$G$17*F26 -> 0 | AG26: =AF26*V26 -> 0 | AH26: =AG26*($I$15/12) -> 0
A27: 5 | F27: =C27*(1+E27) -> 0 | H27: =D27 -> 0 | I27: =IF(I$22=0,"",H27*(1+'B. Basisdaten'!$G$4)) -> 0 | J27: =IF(J$22=0,"",I27*(1+'B. Basisdaten'!$G$4)) -> 0 | K27: =IF(K$22=0,"",J27*(1+'B. Basisdaten'!$G$4)) -> 0 | L27: =IF(L$22=0,"",K27*(1+'B. Basisdaten'!$G$4)) -> 0 | M27: =IF(M$22=0,"",L27*(1+'B. Basisdaten'!$G$4)) -> 0 | N27: =IF(N$22=0,"",M27*(1+'B. Basisdaten'!$G$4)) | O27: =IF(O$22=0,"",N27*(1+'B. Basisdaten'!$G$4)) | P27: =IF(P$22=0,"",O27*(1+'B. Basisdaten'!$G$4)) | Q27: =IF(Q$22=0,"",P27*(1+'B. Basisdaten'!$G$4)) | R27: =SUMPRODUCT(H27:Q27,$H$21:$Q$21)/SUM($H$21:$Q$21) -> 0 | S27: =R27*($C$6+$C$7) -> 0 | T27: =R27+S27 -> 0 | U27: =(R27+S27)*$C$9 -> 0 | V27: =T27+U27 -> 0 | W27: =(R27+S27+U27)/(1-$C$11-$C$13-$C$14)*$C$11 -> 0 | X27: =V27+W27 -> 0 | Y27: =(V27)/(1-$C$11-$C$13-$C$14)*($C$13+$C$14) -> 0 | Z27: =X27+Y27 -> 0 | AA27: =(Z27/(1-$C$16))-Z27 -> 0 | AB27: =SUM(Z27)/(1-$C$16) -> 0 | AC27: =AB27*$C$18 -> 0 | AD27: =AB27+AC27 -> 0 | AF27: ='B. Basisdaten'!$G$17*F27 -> 0 | AG27: =AF27*V27 -> 0 | AH27: =AG27*($I$15/12) -> 0
A28: 6 | F28: =C28*(1+E28) -> 0 | H28: =D28 -> 0 | I28: =IF(I$22=0,"",H28*(1+'B. Basisdaten'!$G$4)) -> 0 | J28: =IF(J$22=0,"",I28*(1+'B. Basisdaten'!$G$4)) -> 0 | K28: =IF(K$22=0,"",J28*(1+'B. Basisdaten'!$G$4)) -> 0 | L28: =IF(L$22=0,"",K28*(1+'B. Basisdaten'!$G$4)) -> 0 | M28: =IF(M$22=0,"",L28*(1+'B. Basisdaten'!$G$4)) -> 0 | N28: =IF(N$22=0,"",M28*(1+'B. Basisdaten'!$G$4)) | O28: =IF(O$22=0,"",N28*(1+'B. Basisdaten'!$G$4)) | P28: =IF(P$22=0,"",O28*(1+'B. Basisdaten'!$G$4)) | Q28: =IF(Q$22=0,"",P28*(1+'B. Basisdaten'!$G$4)) | R28: =SUMPRODUCT(H28:Q28,$H$21:$Q$21)/SUM($H$21:$Q$21) -> 0 | S28: =R28*($C$6+$C$7) -> 0 | T28: =R28+S28 -> 0 | U28: =(R28+S28)*$C$9 -> 0 | V28: =T28+U28 -> 0 | W28: =(R28+S28+U28)/(1-$C$11-$C$13-$C$14)*$C$11 -> 0 | X28: =V28+W28 -> 0 | Y28: =(V28)/(1-$C$11-$C$13-$C$14)*($C$13+$C$14) -> 0 | Z28: =X28+Y28 -> 0 | AA28: =(Z28/(1-$C$16))-Z28 -> 0 | AB28: =SUM(Z28)/(1-$C$16) -> 0 | AC28: =AB28*$C$18 -> 0 | AD28: =AB28+AC28 -> 0 | AF28: ='B. Basisdaten'!$G$17*F28 -> 0 | AG28: =AF28*V28 -> 0 | AH28: =AG28*($I$15/12) -> 0
A29: 7 | F29: =C29*(1+E29) -> 0 | H29: =D29 -> 0 | I29: =IF(I$22=0,"",H29*(1+'B. Basisdaten'!$G$4)) -> 0 | J29: =IF(J$22=0,"",I29*(1+'B. Basisdaten'!$G$4)) -> 0 | K29: =IF(K$22=0,"",J29*(1+'B. Basisdaten'!$G$4)) -> 0 | L29: =IF(L$22=0,"",K29*(1+'B. Basisdaten'!$G$4)) -> 0 | M29: =IF(M$22=0,"",L29*(1+'B. Basisdaten'!$G$4)) -> 0 | N29: =IF(N$22=0,"",M29*(1+'B. Basisdaten'!$G$4)) | O29: =IF(O$22=0,"",N29*(1+'B. Basisdaten'!$G$4)) | P29: =IF(P$22=0,"",O29*(1+'B. Basisdaten'!$G$4)) | Q29: =IF(Q$22=0,"",P29*(1+'B. Basisdaten'!$G$4)) | R29: =SUMPRODUCT(H29:Q29,$H$21:$Q$21)/SUM($H$21:$Q$21) -> 0 | S29: =R29*($C$6+$C$7) -> 0 | T29: =R29+S29 -> 0 | U29: =(R29+S29)*$C$9 -> 0 | V29: =T29+U29 -> 0 | W29: =(R29+S29+U29)/(1-$C$11-$C$13-$C$14)*$C$11 -> 0 | X29: =V29+W29 -> 0 | Y29: =(V29)/(1-$C$11-$C$13-$C$14)*($C$13+$C$14) -> 0 | Z29: =X29+Y29 -> 0 | AA29: =(Z29/(1-$C$16))-Z29 -> 0 | AB29: =SUM(Z29)/(1-$C$16) -> 0 | AC29: =AB29*$C$18 -> 0 | AD29: =AB29+AC29 -> 0 | AF29: ='B. Basisdaten'!$G$17*F29 -> 0 | AG29: =AF29*V29 -> 0 | AH29: =AG29*($I$15/12) -> 0
A30: 8 | F30: =C30*(1+E30) -> 0 | H30: =D30 -> 0 | I30: =IF(I$22=0,"",H30*(1+'B. Basisdaten'!$G$4)) -> 0 | J30: =IF(J$22=0,"",I30*(1+'B. Basisdaten'!$G$4)) -> 0 | K30: =IF(K$22=0,"",J30*(1+'B. Basisdaten'!$G$4)) -> 0 | L30: =IF(L$22=0,"",K30*(1+'B. Basisdaten'!$G$4)) -> 0 | M30: =IF(M$22=0,"",L30*(1+'B. Basisdaten'!$G$4)) -> 0 | N30: =IF(N$22=0,"",M30*(1+'B. Basisdaten'!$G$4)) | O30: =IF(O$22=0,"",N30*(1+'B. Basisdaten'!$G$4)) | P30: =IF(P$22=0,"",O30*(1+'B. Basisdaten'!$G$4)) | Q30: =IF(Q$22=0,"",P30*(1+'B. Basisdaten'!$G$4)) | R30: =SUMPRODUCT(H30:Q30,$H$21:$Q$21)/SUM($H$21:$Q$21) -> 0 | S30: =R30*($C$6+$C$7) -> 0 | T30: =R30+S30 -> 0 | U30: =(R30+S30)*$C$9 -> 0 | V30: =T30+U30 -> 0 | W30: =(R30+S30+U30)/(1-$C$11-$C$13-$C$14)*$C$11 -> 0 | X30: =V30+W30 -> 0 | Y30: =(V30)/(1-$C$11-$C$13-$C$14)*($C$13+$C$14) -> 0 | Z30: =X30+Y30 -> 0 | AA30: =(Z30/(1-$C$16))-Z30 -> 0 | AB30: =SUM(Z30)/(1-$C$16) -> 0 | AC30: =AB30*$C$18 -> 0 | AD30: =AB30+AC30 -> 0 | AF30: ='B. Basisdaten'!$G$17*F30 -> 0 | AG30: =AF30*V30 -> 0 | AH30: =AG30*($I$15/12) -> 0
A31: 9 | F31: =C31*(1+E31) -> 0 | H31: =D31 -> 0 | I31: =IF(I$22=0,"",H31*(1+'B. Basisdaten'!$G$4)) -> 0 | J31: =IF(J$22=0,"",I31*(1+'B. Basisdaten'!$G$4)) -> 0 | K31: =IF(K$22=0,"",J31*(1+'B. Basisdaten'!$G$4)) -> 0 | L31: =IF(L$22=0,"",K31*(1+'B. Basisdaten'!$G$4)) -> 0 | M31: =IF(M$22=0,"",L31*(1+'B. Basisdaten'!$G$4)) -> 0 | N31: =IF(N$22=0,"",M31*(1+'B. Basisdaten'!$G$4)) | O31: =IF(O$22=0,"",N31*(1+'B. Basisdaten'!$G$4)) | P31: =IF(P$22=0,"",O31*(1+'B. Basisdaten'!$G$4)) | Q31: =IF(Q$22=0,"",P31*(1+'B. Basisdaten'!$G$4)) | R31: =SUMPRODUCT(H31:Q31,$H$21:$Q$21)/SUM($H$21:$Q$21) -> 0 | S31: =R31*($C$6+$C$7) -> 0 | T31: =R31+S31 -> 0 | U31: =(R31+S31)*$C$9 -> 0 | V31: =T31+U31 -> 0 | W31: =(R31+S31+U31)/(1-$C$11-$C$13-$C$14)*$C$11 -> 0 | X31: =V31+W31 -> 0 | Y31: =(V31)/(1-$C$11-$C$13-$C$14)*($C$13+$C$14) -> 0 | Z31: =X31+Y31 -> 0 | AA31: =(Z31/(1-$C$16))-Z31 -> 0 | AB31: =SUM(Z31)/(1-$C$16) -> 0 | AC31: =AB31*$C$18 -> 0 | AD31: =AB31+AC31 -> 0 | AF31: ='B. Basisdaten'!$G$17*F31 -> 0 | AG31: =AF31*V31 -> 0 | AH31: =AG31*($I$15/12) -> 0
A32: 10 | F32: =C32*(1+E32) -> 0 | H32: =D32 -> 0 | I32: =IF(I$22=0,"",H32*(1+'B. Basisdaten'!$G$4)) -> 0 | J32: =IF(J$22=0,"",I32*(1+'B. Basisdaten'!$G$4)) -> 0 | K32: =IF(K$22=0,"",J32*(1+'B. Basisdaten'!$G$4)) -> 0 | L32: =IF(L$22=0,"",K32*(1+'B. Basisdaten'!$G$4)) -> 0 | M32: =IF(M$22=0,"",L32*(1+'B. Basisdaten'!$G$4)) -> 0 | N32: =IF(N$22=0,"",M32*(1+'B. Basisdaten'!$G$4)) | O32: =IF(O$22=0,"",N32*(1+'B. Basisdaten'!$G$4)) | P32: =IF(P$22=0,"",O32*(1+'B. Basisdaten'!$G$4)) | Q32: =IF(Q$22=0,"",P32*(1+'B. Basisdaten'!$G$4)) | R32: =SUMPRODUCT(H32:Q32,$H$21:$Q$21)/SUM($H$21:$Q$21) -> 0 | S32: =R32*($C$6+$C$7) -> 0 | T32: =R32+S32 -> 0 | U32: =(R32+S32)*$C$9 -> 0 | V32: =T32+U32 -> 0 | W32: =(R32+S32+U32)/(1-$C$11-$C$13-$C$14)*$C$11 -> 0 | X32: =V32+W32 -> 0 | Y32: =(V32)/(1-$C$11-$C$13-$C$14)*($C$13+$C$14) -> 0 | Z32: =X32+Y32 -> 0 | AA32: =(Z32/(1-$C$16))-Z32 -> 0 | AB32: =SUM(Z32)/(1-$C$16) -> 0 | AC32: =AB32*$C$18 -> 0 | AD32: =AB32+AC32 -> 0 | AF32: ='B. Basisdaten'!$G$17*F32 -> 0 | AG32: =AF32*V32 -> 0 | AH32: =AG32*($I$15/12) -> 0
A33: # | B33: Total | C33: =SUM(C23:C32) -> 18.1625 | F33: =SUM(F23:F32) -> 21.38816 | AF33: =SUM(AF23:AF32) -> 35589.898 | AG33: =SUM(AG23:AG32) -> 1163304.4 | AH33: =SUM(AH23:AH32) -> 5816521.9
AH35: 8446695.4
AH36: =AH33/AH35-1 -> -0.31138491

Sheet II. Sachkosten
B1: II. Sachkosten | D1: Contract Start | E1: ='A. Start'!$E$3 -> 46492 | K1: TO/p.a. | L1: =#REF! -> #REF!
B3: II-1. Investitionen/Einmalkosten | H3: II-2. Monatliche Betriebskosten/Verbräuche | N3: II-4. Nachunternehmerleistung
B4: Name | C4: Menge | D4: Kosten/ Einheit | E4: Gesamtkosten Jahr | F4: Gesamtkosten Laufzeit | H4: Name | I4: Menge | J4: Kosten/ Monat | K4: Gesamtkosten Jahr | L4: Gesamtkosten Laufzeit | N4: Name | O4: Menge | P4: Kosten /Jahr | Q4: Gesamtkosten Jahr | R4: Gesamtkosten Laufzeit
B5: Lagertechnik lt. Stückliste (Lagerplaner) | C5: 1 | D5: 850000 | E5: =F5/'A. Start'!$E$5*12 -> 170000 | F5: =C5*D5 -> 850000 | H5: Hallenmiete | I5: 1 | J5: 78500 | K5: =J5*I5*12 -> 942000 | L5: =K5*'A. Start'!$E$6 -> 4710000 | N5: Wachdienst | O5: 1 | P5: 96000 | Q5: =P5*O5 -> 96000 | R5: =Q5*'A. Start'!$E$6 -> 480000
B6: IT-Ausstattung | C6: 12 | D6: 1450.5 | E6: =F6/'A. Start'!$E$5*12 -> 3481.2 | F6: =C6*D6 -> 17406 | H6: Staplerleasing | I6: 9 | J6: 1150 | K6: =J6*I6*12 -> 124200 | L6: =K6*'A. Start'!$E$6 -> 621000 | Q6: =P6*O6 -> 0 | R6: =Q6*'A. Start'!$E$6 -> 0
E7: =F7/'A. Start'!$E$5*12 -> 0 | F7: =C7*D7 -> 0 | H7: Energie | I7: 1 | J7: 6200 | K7: =J7*I7*12 -> 74400 | L7: =K7*'A. Start'!$E$6 -> 372000 | Q7: =P7*O7 -> 0 | R7: =Q7*'A. Start'!$E$6 -> 0
E8: =F8/'A. Start'!$E$5*12 -> 0 | F8: =C8*D8 -> 0 | K8: =J8*I8*12 -> 0 | L8: =K8*'A. Start'!$E$6 -> 0 | Q8: =P8*O8 -> 0 | R8: =Q8*'A. Start'!$E$6 -> 0
E9: =F9/'A. Start'!$E$5*12 -> 0 | F9: =C9*D9 -> 0 | K9: =J9*I9*12 -> 0 | L9: =K9*'A. Start'!$E$6 -> 0 | Q9: =P9*O9 -> 0 | R9: =Q9*'A. Start'!$E$6 -> 0
E10: =F10/'A. Start'!$E$5*12 -> 0 | F10: =C10*D10 -> 0 | K10: =J10*I10*12 -> 0 | L10: =K10*'A. Start'!$E$6 -> 0 | Q10: =P10*O10 -> 0 | R10: =Q10*'A. Start'!$E$6 -> 0
E11: =F11/'A. Start'!$E$5*12 -> 0 | F11: =C11*D11 -> 0 | K11: =J11*I11*12 -> 0 | L11: =K11*'A. Start'!$E$6 -> 0 | Q11: =P11*O11 -> 0 | R11: =Q11*'A. Start'!$E$6 -> 0
E12: =F12/'A. Start'!$E$5*12 -> 0 | F12: =C12*D12 -> 0 | K12: =J12*I12*12 -> 0 | L12: =K12*'A. Start'!$E$6 -> 0 | Q12: =P12*O12 -> 0 | R12: =Q12*'A. Start'!$E$6 -> 0
E13: =F13/'A. Start'!$E$5*12 -> 0 | F13: =C13*D13 -> 0 | K13: =J13*I13*12 -> 0 | L13: =K13*'A. Start'!$E$6 -> 0 | Q13: =P13*O13 -> 0 | R13: =Q13*'A. Start'!$E$6 -> 0
E14: =F14/'A. Start'!$E$5*12 -> 0 | F14: =C14*D14 -> 0 | K14: =J14*I14*12 -> 0 | L14: =K14*'A. Start'!$E$6 -> 0 | Q14: =P14*O14 -> 0 | R14: =Q14*'A. Start'!$E$6 -> 0
E15: =F15/'A. Start'!$E$5*12 -> 0 | F15: =C15*D15 -> 0 | K15: =J15*I15*12 -> 0 | L15: =K15*'A. Start'!$E$6 -> 0 | Q15: =P15*O15 -> 0 | R15: =Q15*'A. Start'!$E$6 -> 0
E16: =F16/'A. Start'!$E$5*12 -> 0 | F16: =C16*D16 -> 0 | K16: =J16*I16*12 -> 0 | L16: =K16*'A. Start'!$E$6 -> 0 | Q16: =P16*O16 -> 0 | R16: =Q16*'A. Start'!$E$6 -> 0
E17: =F17/'A. Start'!$E$5*12 -> 0 | F17: =C17*D17 -> 0 | K17: =J17*I17*12 -> 0 | L17: =K17*'A. Start'!$E$6 -> 0 | Q17: =P17*O17 -> 0 | R17: =Q17*'A. Start'!$E$6 -> 0
E18: =F18/'A. Start'!$E$5*12 -> 0 | F18: =C18*D18 -> 0 | K18: =J18*I18*12 -> 0 | L18: =K18*'A. Start'!$E$6 -> 0 | Q18: =P18*O18 -> 0 | R18: =Q18*'A. Start'!$E$6 -> 0
E19: =F19/'A. Start'!$E$5*12 -> 0 | F19: =C19*D19 -> 0 | K19: =J19*I19*12 -> 0 | L19: =K19*'A. Start'!$E$6 -> 0 | Q19: =P19*O19 -> 0 | R19: =Q19*'A. Start'!$E$6 -> 0
B20: Summe | E20: =SUM(E5:E19) -> 173481.2 | F20: =SUM(F5:F19) -> 867406 | H20: Summe | K20: =SUM(K5:K19) -> 1140600 | L20: =SUM(L5:L19) -> 5703000 | N20: Summe | Q20: =SUM(Q5:Q19) -> 96000 | R20: =SUM(R5:R19) -> 480000
B22: II-5. Ramp-Up Gesamtkosten | C22: 1 | D22: 100000 | E22: =F22/'A. Start'!$E$5*12 -> 20000 | F22: =C22*D22 -> 100000

Sheet V. Summary
B1: Summary Kalkulation | C1: =_xlfn.TEXTJOIN(" / ",TRUE(),'A. Start'!B8,'A. Start'!B9) -> VIAS / LOG | E1: Kalulationsdatum | F1: ='A. Start'!E8 -> 46111
B3: ='A. Start'!A3 -> Projektname | C3: ='A. Start'!B3 -> Testkalkulation Kombinationen | E3: ='A. Start'!D3 -> Start Leistung | F3: ='A. Start'!E3 -> 46492
B4: ='A. Start'!A4 -> Kundenname | C4: ='A. Start'!B4 -> Testkunde | E4: ='A. Start'!D4 -> Ende Leistung | F4: ='A. Start'!E4 -> 48318
B5: ='A. Start'!A5 -> Projektstandort | C5: ='A. Start'!B5 -> UT | E5: ='A. Start'!D5 -> Laufzeit [Monate] | F5: ='A. Start'!E5 -> 60
B7: HV-Umlage | C7: ='B. Basisdaten'!C8 -> 0.05 | E7: ='B. Basisdaten'!B4 -> Gewinn | F7: ='B. Basisdaten'!C4 -> 0.05
B8: BU-Umlage | C8: ='B. Basisdaten'!C9 -> 0.025 | E8: ='B. Basisdaten'!B5 -> Risiko (Leadec Global C2 = 1,00%) | F8: ='B. Basisdaten'!C5 -> 0.01
B9: NL-Umlage | C9: ='B. Basisdaten'!C10 -> 0.02 | E9: ='B. Basisdaten'!B13 -> Verhandlungsmarge | F9: ='B. Basisdaten'!C13 -> 0.06
E10: Net | F10: Brutto/Gross | G10: Produktive Jahresstunden
B11: TO/p.a. mit Verhandlung | C11: =D30 -> 3818013.2 | D11: FTE Gehälter | E11: ='I-1. FTE-Gehälter'!C33 -> 4.5 | F11: ='I-1. FTE-Gehälter'!F33 -> 4.9 | G11: ='I-1. FTE-Gehälter'!AF33 -> 7949.76
B12: TO/Laufzeit mit Verhandlung | C12: =E30 -> 19090066 | D12: FTE Löhne | E12: ='I-2. FTE-Löhne'!C33 -> 18.1625 | F12: ='I-2. FTE-Löhne'!F33 -> 21.38816 | G12: ='I-2. FTE-Löhne'!AF33 -> 35589.898
B13: Umsatz/FTE | C13: =C11/E13 -> 168472.73 | D13: ∑FTE | E13: =E12+E11 -> 22.6625 | F13: =F12+F11 -> 26.28816 | G13: =G12+G11 -> 43539.658
B16: Summary Kalkulation | C16: %-Anteile | D16: Pro Jahr (p.a) | E16: Laufzeit | F16: Produktive Stunde
B17: ='I-1. FTE-Gehälter'!B1 -> I-1. Personalkosten Gehälter | C17: =E17/$E$25 -> 0.13020595 | D17: ='I-1. FTE-Gehälter'!AG33 -> 439262.34 | E17: =D17*($F$5/12) -> 2196311.7 | F17: =D17/G11 -> 55.254792 | G17: 2382312.9
B18: ='I-2. FTE-Löhne'!B1 -> I-2. Personalkosten Löhne | C18: =E18/$E$25 -> 0.34482618 | D18: ='I-2. FTE-Löhne'!AG33 -> 1163304.4 | E18: =D18*($F$5/12) -> 5816521.9 | F18: =D18/G12 -> 32.686365 | G18: 8446695.4
B19: ='II. Sachkosten'!B3 -> II-1. Investitionen/Einmalkosten | C19: =E19/$E$25 -> 0.051423221 | D19: ='II. Sachkosten'!E20 -> 173481.2 | E19: ='II. Sachkosten'!F20 -> 867406 | F19: =D19/$G$13 -> 3.984441
B20: ='II. Sachkosten'!H3 -> II-2. Monatliche Betriebskosten/Verbräuche | C20: =E20/$E$25 -> 0.33809615 | D20: ='II. Sachkosten'!K20 -> 1140600 | E20: ='II. Sachkosten'!L20 -> 5703000 | F20: =D20/$G$13 -> 26.196806
B21: ='II. Sachkosten'!N3 -> II-4. Nachunternehmerleistung | C21: =E21/$E$25 -> 0.028456278 | D21: ='II. Sachkosten'!Q20 -> 96000 | E21: ='II. Sachkosten'!R20 -> 480000 | F21: =D21/$G$13 -> 2.2048864
B22: ='II. Sachkosten'!B22 -> II-5. Ramp-Up Gesamtkosten | C22: =E22/$E$25 -> 0.0059283912 | D22: ='II. Sachkosten'!E22 -> 20000 | E22: ='II. Sachkosten'!F22 -> 100000 | F22: =D22/$G$13 -> 0.45935133
B23: Projektkosten | C23: =E23/$E$25 -> 0.89893617 | D23: =SUM(D17:D22) -> 3032647.9 | E23: =SUM(E17:E22) -> 15163240 | F23: =D23/$G$13 -> 69.652543
A24: =E24/E28 -> 0.095 | B24: Unternehmensumlagen (HV/BU/NL) | C24: =E24/$E$25 -> 0.10106383 | D24: =(D23/(1-$F$7-$F$8-SUM($C$7:$C$9))*SUM($C$7:$C$9)) -> 340948.58 | E24: =(E23/(1-$F$7-$F$8-SUM($C$7:$C$9))*SUM($C$7:$C$9)) -> 1704742.9 | F24: =D24/$G$13 -> 7.8307593 | G24: 2665898.5
B25: ∑Selbstkosten | C25: =E25/$E$25 -> 1 | D25: =D23+D24 -> 3373596.5 | E25: =E23+E24 -> 16867983 | F25: =D25/$G$13 -> 77.483302
B26: Gewinn | C26: =E26/$E$28 -> 0.05 | D26: =(D23/(1-$F$7-$F$8-SUM($C$7:$C$9))*$F$7) -> 179446.62 | E26: =(E23/(1-$F$7-$F$8-SUM($C$7:$C$9))*$F$7) -> 897233.11 | F26: =D26/$G$13 -> 4.1214523 | G26: 1599539.1
B27: Risiko | C27: =E27/$E$28 -> 0.01 | D27: =(D23/(1-$F$7-$F$8-SUM($C$7:$C$9))*$F$8) -> 35889.325 | E27: =(E23/(1-$F$7-$F$8-SUM($C$7:$C$9))*$F$8) -> 179446.62 | F27: =D27/$G$13 -> 0.82429045 | G27: 533179.7
B28: Umsatz ohne Verhandlung | C28: =E28/$E$25 -> 1.0638298 | D28: =D25+D26+D27 -> 3588932.5 | E28: =E25+E26+E27 -> 17944662 | F28: =D28/$G$13 -> 82.429045 | G28: 26658985
B29: Verhandlung | C29: =E29/$E$30 -> 0.06 | D29: =$F$9*((D23/(1-$F$7-$F$8-SUM($C$7:$C$9))))/(1-$F$9) -> 229080.79 | E29: =$F$9*((E23/(1-$F$7-$F$8-SUM($C$7:$C$9))))/(1-$F$9) -> 1145404 | F29: =D29/$G$13 -> 5.2614284 | G29: 2318172.6
B30: Umsatz mit Verhandlung | C30: =E30/E25 -> 1.1317338 | D30: =D28+D29 -> 3818013.2 | E30: =E28+E29 -> 19090066 | F30: =D30/$G$13 -> 87.690474 | G30: 28977158 | H30: =E30/G30-1 -> -0.34120294
B32: OtO-Wert Angebots-TO | C32: %-Anteilie | D32: pro Jahr (p.a)
B33: UMSATZ mit Verhandlung | D33: =D30 -> 3818013.2
B34: EBITA Gewinn+Verhandlung | C34: =D34/D33 -> 0.107 | D34: =D26+D29 -> 408527.42
B35: Gross Profit EBITA+HV+BU | C35: =C34+C7+C8 -> 0.182 | D35: =C35*D33 -> 694878.41
B37: OtO-Wert Walkaway-Price
B38: UMSATZ ohne Verhandlung | D38: =D28 -> 3588932.5
B39: EBITA Gewinn | C39: =D39/D38 -> 0.05 | D39: =D26 -> 179446.62
B40: Gross Profit EBITA+HV+BU | C40: =C39+C7+C8 -> 0.125 | D40: =C40*D38 -> 448616.56

Sheet VI. OtO
A1: OtO-Werte | I1: OtO-Abgabeunterlage bitte aus Ordner kopieren und als separate Datei anlegen: | L1: LINK
B3: Opportunity Informationen I
B5: Angebots-/Auftragsdatum | Date | D5: dd.mm.yyyy
B6: Status | Status | D6: Angebot
B7: Gesellschaft | Business Unit | D7: ='A. Start'!B8 -> VIAS
B8: SFDC-Nr. | I8: Werte in separate Datei kopieren!
B9: Kunde/ Account | Customer | D9: ='A. Start'!B4 -> Testkunde
B10: Umfang | Opportunity Name | D10: ='A. Start'!B3 -> Testkalkulation Kombinationen
B11: Kalkulation von | Calculated by | D11: ='A. Start'!E9 -> Kästner
B12: Service Line | Service Line | D12: ='A. Start'!B9 -> LOG
B13: Angebotsnummer | Offer Number
B14: Angebotswährung | offer currency | D14: EUR
B15: Wechselkurs | exchange rate | D15: 1
B16: Zuschlag HV+BU | Contribution | D16: ='B. Basisdaten'!$C$8+'B. Basisdaten'!$C$9 -> 0.075
B18: Angebots TO | Offer TO
B19: ='V. Summary'!D33 -> 3818013.2 | C19: =D14 -> EUR | D19: ¬ Rahmenvertrag: Jahresvolumen ¬ Projektgeschäft: Gesamtvolumen
B20: Gross Profit | Bruttogewinn | D20: Gross Margin
B21: ='V. Summary'!D35 -> 694878.41 | C21: =C19 -> EUR | D21: =B21/B19 -> 0.182
B22: EBITA (excl. Zinsen) | EBITA (excl. interest rates) | D22: EBITA Margin | G22: =D21-D23 -> 0.075
B23: ='V. Summary'!D34 -> 408527.42 | C23: =C19 -> EUR | D23: =B23/B19 -> 0.107
B24: Investment (total netto) | Invest (total net)
B25: ='V. Summary'!E19 -> 867406 | C25: =C19 -> EUR
B26: Leasing p.a. | Leasing p.a.
B27: ='V. Summary'!D20 -> 1140600 | C27: =C21 -> EUR
B28: Abrechnungsart | Payment model
B31: Approval Process inkl. Vertragsprüfung
B33: Opportunity Informationen II
B34: Walkaway-/Verhandlungspreis
B35: ='V. Summary'!D38 -> 3588932.5 | C35: =C19 -> EUR
B36: Walkaway Gross Profit | D36: Gross Margin
B37: ='V. Summary'!D40 -> 448616.56 | C37: =C35 -> EUR | D37: =B37/B35 -> 0.125
B38: Walkaway EBITA | D38: EBITA Margin | G38: =D37-D39 -> 0.075
B39: ='V. Summary'!D39 -> 179446.62 | C39: =C35 -> EUR | D39: =B39/B35 -> 0.05
B40: Investment
B41: =B25 -> 867406 | C41: =C35 -> EUR
B42: Leasing
B43: =B27 -> 1140600 | C43: =C35 -> EUR

Sheet Tabelle1
F2: Q1 | G2: Q2
B3: Qualifikation
B4: Netto | D4: SV-Pflichtig | E4: Grundlohn | M4: Projektumsatz pa | N4: : | O4: FTExProduktivstunden/FTE pa
B5: Brutto | E5: Soziallöhne | G5: bezahlte Abwesenheit | N5: VK-Stundensatz
E6: Schichtzuschlag | G6: Nachtschicht etc
E7: Prämie | G7: Prämie
G8: AN-Brutto-Lohn
D9: SV-Zuschläge | E9: Summe SV | F9: 0.238
G10: AG-Brutto-Lohn
E11: MGK-Zuschlag
G12: AG-Lohn+MGK
D13: HV, BU, NL
D14: Risiko
G15: Selbstkosten
D16: Gewinn
D17: Verhandlung
G18: Mitarbeiterstundensatz im Verkauf mit Materaial
E19: - MGK +SK-Zuschlag | G19: Mitarbeiterstundensatz im Verkauf mit Materaial
D28: Qualitfikati | E28: FTE | F28: Brutto-F | G28: Grundlohn | H28: [SV-pflichtig] | I28: [SV-Z AG | J28: =AG-Brutto-Lohn | K28: [SK-Zuschläg] | L28: [G+VV] | M28: = VSSoM | O28: MGK | P28: [SK+G+V] | Q28: =MGK-Z[€] | S28: VSSoM+MGK-Z?=VSSmM
H29: % | I29: % | K29: % | L29: % | O29: % | P29: %
